codewars_scraper/__init__.py
codewars_scraper/__main__.py
codewars_scraper/file_extensions.py
codewars_scraper/scraper.py
codewars_scraper/speedups.py
codewars_scraper-1.0.dist-info/entry_points.txt
codewars_scraper-1.0.dist-info/LICENSE
codewars_scraper-1.0.dist-info/WHEEL
codewars_scraper-1.0.dist-info/METADATA
codewars_scraper-1.0.dist-info/RECORD
